Workbook

Sheet Assumptions
A1: Microsoft Corporation (NASDAQ: MSFT) - Integrated 5-Year 3-Statement Model
A2: Currency: USD in millions; fiscal years ending June 30; forecasts linked to assumptions; built 2026-05-23
A4: Assumption / Driver | B4: Units | C4: FY24A | D4: FY25E | E4: FY26E | F4: FY27E | G4: FY28E | H4: FY29E | I4: Source / Notes
A5: REVENUE BY SEGMENT
A6: Productivity & Business Processes Revenue | B6: $mm | C6: 77728 | D6: =C6*(1+D10) -> 87055.36 | E6: =D6*(1+E10) -> 96631.45 | F6: =E6*(1+F10) -> 106294.59 | G6: =F6*(1+G10) -> 115861.11 | H6: =G6*(1+H10) -> 125130 | I6: FY24 actual per Microsoft FY24 Q4 segment revenue; forecast = prior year x segment growth
A7: Intelligent Cloud Revenue | B7: $mm | C7: 105362 | D7: =C7*(1+D11) -> 126434.4 | E7: =D7*(1+E11) -> 149192.59 | F7: =E7*(1+F11) -> 173063.41 | G7: =F7*(1+G11) -> 197292.28 | H7: =G7*(1+H11) -> 220967.36 | I7: FY24 actual per Microsoft FY24 Q4 segment revenue; forecast = prior year x segment growth
A8: More Personal Computing Revenue | B8: $mm | C8: 62032 | D8: =C8*(1+D12) -> 66994.56 | E8: =D8*(1+E12) -> 71014.234 | F8: =E8*(1+F12) -> 74564.945 | G8: =F8*(1+G12) -> 77547.543 | H8: =G8*(1+H12) -> 79873.969 | I8: FY24 actual per Microsoft FY24 Q4 segment revenue; forecast = prior year x segment growth
A9: Total Revenue | B9: $mm | C9: =SUM(C6:C8) -> 245122 | D9: =SUM(D6:D8) -> 280484.32 | E9: =SUM(E6:E8) -> 316838.28 | F9: =SUM(F6:F8) -> 353922.95 | G9: =SUM(G6:G8) -> 390700.93 | H9: =SUM(H6:H8) -> 425971.32 | I9: FY24 total rounds to user-provided $245.12bn
A10: Productivity & Business Processes Revenue Growth | B10: % | D10: 0.12 | E10: 0.11 | F10: 0.1 | G10: 0.09 | H10: 0.08 | I10: Assumption: commercial cloud and Office/LinkedIn growth moderates
A11: Intelligent Cloud Revenue Growth | B11: % | D11: 0.2 | E11: 0.18 | F11: 0.16 | G11: 0.14 | H11: 0.12 | I11: Assumption: Azure/AI demand drives above-company growth with moderation
A12: More Personal Computing Revenue Growth | B12: % | D12: 0.08 | E12: 0.06 | F12: 0.05 | G12: 0.04 | H12: 0.03 | I12: Assumption: Windows/devices/gaming normalize after FY24 Activision contribution
A14: MARGINS, EXPENSES, TAX, AND INTEREST
A15: Gross Margin | B15: % | C15: =171008/C9 -> 0.69764444 | D15: 0.69 | E15: 0.688 | F15: 0.688 | G15: 0.69 | H15: 0.692 | I15: FY24 actual from revenue and cost of revenue; forecast assumes AI infrastructure pressure then scale benefits
A16: R&D % of Revenue | B16: % | C16: =29510/C9 -> 0.12038903 | D16: 0.125 | E16: 0.123 | F16: 0.121 | G16: 0.12 | H16: 0.118 | I16: FY24 actual per Microsoft income statement; forecast assumes operating leverage
A17: S&M % of Revenue | B17: % | C17: =24456/C9 -> 0.099770726 | D17: 0.1 | E17: 0.098 | F17: 0.096 | G17: 0.095 | H17: 0.094 | I17: FY24 actual per Microsoft income statement; forecast assumes go-to-market leverage
A18: G&A % of Revenue | B18: % | C18: =7609/C9 -> 0.031041685 | D18: 0.03 | E18: 0.029 | F18: 0.028 | G18: 0.027 | H18: 0.027 | I18: FY24 actual per Microsoft income statement; forecast assumes fixed-cost leverage
A19: Cash Tax Rate | B19: % | C19: =19651/(109433-2935+1289) -> 0.18231327 | D19: 0.182 | E19: 0.182 | F19: 0.182 | G19: 0.182 | H19: 0.182 | I19: FY24 derived from pretax income less tax expense; forecast held flat
A20: Interest Rate on Debt | B20: % | C20: =2935/42688 -> 0.068754685 | D20: 0.04 | E20: 0.04 | F20: 0.04 | G20: 0.04 | H20: 0.04 | I20: Forecast assumption based on investment-grade borrowing cost
A22: WORKING CAPITAL DAYS
A23: DSO | B23: days | C23: =56924/C9*365 -> 84.762934 | D23: 84 | E23: 83 | F23: 82 | G23: 82 | H23: 81 | I23: Forecast assumes slight improvement in collections
A24: DIO | B24: days | C24: =1246/74114*365 -> 6.1363575 | D24: 6 | E24: 6 | F24: 6 | G24: 6 | H24: 6 | I24: Inventory remains immaterial vs services mix
A25: Current Liabilities Days | B25: days | C25: =125286/C9*365 -> 186.55767 | D25: 185 | E25: 184 | F25: 183 | G25: 182 | H25: 181 | I25: Uses total current liabilities as simplified working capital proxy
A27: CASH FLOW AND BALANCE SHEET DRIVERS
A28: D&A % of Revenue | B28: % | C28: =22287/C9 -> 0.090922071 | D28: 0.09 | E28: 0.088 | F28: 0.086 | G28: 0.084 | H28: 0.082 | I28: FY24 actual per cash flow statement; forecast follows data center capex base
A29: CapEx % of Revenue | B29: % | C29: =44477/C9 -> 0.18144842 | D29: 0.18 | E29: 0.17 | F29: 0.16 | G29: 0.15 | H29: 0.14 | I29: Forecast assumes AI/data center investment remains elevated but normalizes
A30: Acquisition Spend % of Revenue | B30: % | C30: =69132/C9 -> 0.28203099 | D30: 0.005 | E30: 0.005 | F30: 0.005 | G30: 0.005 | H30: 0.005 | I30: Forecast assumes modest bolt-on M&A after FY24 Activision close
A31: Dividend Payout % of Net Income | B31: % | C31: =21771/88136 -> 0.24701598 | D31: 0.25 | E31: 0.25 | F31: 0.25 | G31: 0.25 | H31: 0.25 | I31: Forecast assumes consistent payout policy
A32: Share Repurchase % of Revenue | B32: % | C32: =17254/C9 -> 0.070389439 | D32: 0.06 | E32: 0.06 | F32: 0.06 | G32: 0.06 | H32: 0.06 | I32: Forecast assumes buybacks remain a capital return priority
A33: Debt Issuance / (Repayment), Net | B33: $mm | C33: 24395 | D33: 0 | E33: 0 | F33: 0 | G33: 0 | H33: 0 | I33: Forecast assumes no net debt issuance or repayment
A34: SBC / Other Equity Adj. % of Revenue | B34: % | C34: =10734/C9 -> 0.043790439 | D34: 0.04 | E34: 0.039 | F34: 0.038 | G34: 0.037 | H34: 0.036 | I34: Forecast proxy for stock-based comp and other equity adjustments
A35: Other Current Assets % of Revenue | B35: % | C35: =21064/C9 -> 0.085932719 | D35: 0.085 | E35: 0.083 | F35: 0.081 | G35: 0.079 | H35: 0.077 | I35: Residual current asset line; FY24 adjusted to retain user-provided $80.5bn cash base
A36: Other Non-current Assets % of Revenue | B36: % | C36: =97618/C9 -> 0.39824251 | D36: 0.39 | E36: 0.38 | F36: 0.37 | G36: 0.36 | H36: 0.35 | I36: Residual non-current asset line for leases, investments, intangibles and other assets

Sheet Income Statement
A1: Microsoft Corporation - Income Statement
A2: USD in millions; forecasts formula-driven from Assumptions
A4: Line Item | B4: Units | C4: FY24A | D4: FY25E | E4: FY26E | F4: FY27E | G4: FY28E | H4: FY29E
A5: REVENUE
A6: Productivity & Business Processes Revenue | B6: $mm | C6: =Assumptions!C6 -> 77728 | D6: =Assumptions!D6 -> 87055.36 | E6: =Assumptions!E6 -> 96631.45 | F6: =Assumptions!F6 -> 106294.59 | G6: =Assumptions!G6 -> 115861.11 | H6: =Assumptions!H6 -> 125130
A7: Intelligent Cloud Revenue | B7: $mm | C7: =Assumptions!C7 -> 105362 | D7: =Assumptions!D7 -> 126434.4 | E7: =Assumptions!E7 -> 149192.59 | F7: =Assumptions!F7 -> 173063.41 | G7: =Assumptions!G7 -> 197292.28 | H7: =Assumptions!H7 -> 220967.36
A8: More Personal Computing Revenue | B8: $mm | C8: =Assumptions!C8 -> 62032 | D8: =Assumptions!D8 -> 66994.56 | E8: =Assumptions!E8 -> 71014.234 | F8: =Assumptions!F8 -> 74564.945 | G8: =Assumptions!G8 -> 77547.543 | H8: =Assumptions!H8 -> 79873.969
A9: Total Revenue | B9: $mm | C9: 245122 | D9: =SUM(D6:D8) -> 280484.32 | E9: =SUM(E6:E8) -> 316838.28 | F9: =SUM(F6:F8) -> 353922.95 | G9: =SUM(G6:G8) -> 390700.93 | H9: =SUM(H6:H8) -> 425971.32
A10: Revenue Growth | B10: % | D10: =D9/C9-1 -> 0.14426416 | E10: =E9/D9-1 -> 0.12961136 | F10: =F9/E9-1 -> 0.11704606 | G10: =G9/F9-1 -> 0.10391524 | H10: =H9/G9-1 -> 0.090274647
A12: PROFITABILITY
A13: Cost of Revenue | B13: $mm | C13: 74114 | D13: =D9*(1-Assumptions!D15) -> 86950.139 | E13: =E9*(1-Assumptions!E15) -> 98853.542 | F13: =F9*(1-Assumptions!F15) -> 110423.96 | G13: =G9*(1-Assumptions!G15) -> 121117.29 | H13: =H9*(1-Assumptions!H15) -> 131199.17
A14: Gross Profit | B14: $mm | C14: =C9-C13 -> 171008 | D14: =D9-D13 -> 193534.18 | E14: =E9-E13 -> 217984.73 | F14: =F9-F13 -> 243498.99 | G14: =G9-G13 -> 269583.65 | H14: =H9-H13 -> 294772.16
A15: Gross Margin | B15: % | C15: =C14/C9 -> 0.69764444 | D15: =D14/D9 -> 0.69 | E15: =E14/E9 -> 0.688 | F15: =F14/F9 -> 0.688 | G15: =G14/G9 -> 0.69 | H15: =H14/H9 -> 0.692
A17: OPERATING EXPENSES
A18: Research & Development | B18: $mm | C18: 29510 | D18: =D9*Assumptions!D16 -> 35060.54 | E18: =E9*Assumptions!E16 -> 38971.108 | F18: =F9*Assumptions!F16 -> 42824.677 | G18: =G9*Assumptions!G16 -> 46884.112 | H18: =H9*Assumptions!H16 -> 50264.616
A19: Sales & Marketing | B19: $mm | C19: 24456 | D19: =D9*Assumptions!D17 -> 28048.432 | E19: =E9*Assumptions!E17 -> 31050.151 | F19: =F9*Assumptions!F17 -> 33976.603 | G19: =G9*Assumptions!G17 -> 37116.589 | H19: =H9*Assumptions!H17 -> 40041.304
A20: General & Administrative | B20: $mm | C20: 7609 | D20: =D9*Assumptions!D18 -> 8414.5296 | E20: =E9*Assumptions!E18 -> 9188.31 | F20: =F9*Assumptions!F18 -> 9909.8425 | G20: =G9*Assumptions!G18 -> 10548.925 | H20: =H9*Assumptions!H18 -> 11501.226
A21: Total Operating Expenses | B21: $mm | C21: =SUM(C18:C20) -> 61575 | D21: =SUM(D18:D20) -> 71523.502 | E21: =SUM(E18:E20) -> 79209.569 | F21: =SUM(F18:F20) -> 86711.122 | G21: =SUM(G18:G20) -> 94549.626 | H21: =SUM(H18:H20) -> 101807.15
A22: Operating Income | B22: $mm | C22: 109433 | D22: =D14-D21 -> 122010.68 | E22: =E14-E21 -> 138775.16 | F22: =F14-F21 -> 156787.87 | G22: =G14-G21 -> 175034.02 | H22: =H14-H21 -> 192965.01
A23: Operating Margin | B23: % | C23: =C22/C9 -> 0.446443 | D23: =D22/D9 -> 0.435 | E23: =E22/E9 -> 0.438 | F23: =F22/F9 -> 0.443 | G23: =G22/G9 -> 0.448 | H23: =H22/H9 -> 0.453
A25: BELOW OPERATING INCOME
A26: Interest Expense | B26: $mm | C26: 2935 | D26: =AVERAGE('Balance Sheet'!C23:D23)*Assumptions!D20 -> 1707.52 | E26: =AVERAGE('Balance Sheet'!D23:E23)*Assumptions!E20 -> 1707.52 | F26: =AVERAGE('Balance Sheet'!E23:F23)*Assumptions!F20 -> 1707.52 | G26: =AVERAGE('Balance Sheet'!F23:G23)*Assumptions!G20 -> 1707.52 | H26: =AVERAGE('Balance Sheet'!G23:H23)*Assumptions!H20 -> 1707.52
A27: Other Income / (Expense), Net | B27: $mm | C27: 1289 | D27: 0 | E27: 0 | F27: 0 | G27: 0 | H27: 0
A28: Pre-tax Income | B28: $mm | C28: =C22-C26+C27 -> 107787 | D28: =D22-D26+D27 -> 120303.16 | E28: =E22-E26+E27 -> 137067.64 | F28: =F22-F26+F27 -> 155080.35 | G28: =G22-G26+G27 -> 173326.5 | H28: =H22-H26+H27 -> 191257.49
A29: Tax Expense | B29: $mm | C29: 19651 | D29: =D28*Assumptions!D19 -> 21895.175 | E29: =E28*Assumptions!E19 -> 24946.311 | F29: =F28*Assumptions!F19 -> 28224.623 | G29: =G28*Assumptions!G19 -> 31545.423 | H29: =H28*Assumptions!H19 -> 34808.863
A30: Net Income | B30: $mm | C30: 88136 | D30: =D28-D29 -> 98407.984 | E30: =E28-E29 -> 112121.33 | F30: =F28-F29 -> 126855.72 | G30: =G28-G29 -> 141781.08 | H30: =H28-H29 -> 156448.63

Sheet Balance Sheet
A1: Microsoft Corporation - Balance Sheet
A2: USD in millions; cash links to Cash Flow Statement ending cash; simplified residual rows capture omitted detailed lines
A4: Line Item | B4: Units | C4: FY24A | D4: FY25E | E4: FY26E | F4: FY27E | G4: FY28E | H4: FY29E
A5: CURRENT ASSETS
A6: Cash, Cash Equivalents & Investments | B6: $mm | C6: 80500 | D6: ='Cash Flow Statement'!D25 -> 131118.44 | E6: ='Cash Flow Statement'!E25 -> 190854.82 | F6: ='Cash Flow Statement'!F25 -> 260321.99 | G6: ='Cash Flow Statement'!G25 -> 338862.63 | H6: ='Cash Flow Statement'!H25 -> 428636.99
A7: Accounts Receivable | B7: $mm | C7: 56924 | D7: ='Income Statement'!D9*Assumptions!D23/365 -> 64549.816 | E7: ='Income Statement'!E9*Assumptions!E23/365 -> 72048.156 | F7: ='Income Statement'!F9*Assumptions!F23/365 -> 79511.456 | G7: ='Income Statement'!G9*Assumptions!G23/365 -> 87773.909 | H7: ='Income Statement'!H9*Assumptions!H23/365 -> 94530.623
A8: Inventory | B8: $mm | C8: 1246 | D8: ='Income Statement'!D13*Assumptions!D24/365 -> 1429.3174 | E8: ='Income Statement'!E13*Assumptions!E24/365 -> 1624.9897 | F8: ='Income Statement'!F13*Assumptions!F24/365 -> 1815.1884 | G8: ='Income Statement'!G13*Assumptions!G24/365 -> 1990.9691 | H8: ='Income Statement'!H13*Assumptions!H24/365 -> 2156.6986
A9: Other Current Assets | B9: $mm | C9: 21064 | D9: ='Income Statement'!D9*Assumptions!D35 -> 23841.167 | E9: ='Income Statement'!E9*Assumptions!E35 -> 26297.577 | F9: ='Income Statement'!F9*Assumptions!F35 -> 28667.759 | G9: ='Income Statement'!G9*Assumptions!G35 -> 30865.374 | H9: ='Income Statement'!H9*Assumptions!H35 -> 32799.792
A10: Total Current Assets | B10: $mm | C10: =SUM(C6:C9) -> 159734 | D10: =SUM(D6:D9) -> 220938.74 | E10: =SUM(E6:E9) -> 290825.55 | F10: =SUM(F6:F9) -> 370316.39 | G10: =SUM(G6:G9) -> 459492.89 | H10: =SUM(H6:H9) -> 558124.1
A12: NON-CURRENT ASSETS
A13: PP&E, Net | B13: $mm | C13: 135591 | D13: =C13-'Cash Flow Statement'!D13-'Cash Flow Statement'!D7 -> 160834.59 | E13: =D13-'Cash Flow Statement'!E13-'Cash Flow Statement'!E7 -> 186815.33 | F13: =E13-'Cash Flow Statement'!F13-'Cash Flow Statement'!F7 -> 213005.63 | G13: =F13-'Cash Flow Statement'!G13-'Cash Flow Statement'!G7 -> 238791.89 | H13: =G13-'Cash Flow Statement'!H13-'Cash Flow Statement'!H7 -> 263498.22
A14: Goodwill | B14: $mm | C14: 119220 | D14: =C14-'Cash Flow Statement'!D14 -> 120622.42 | E14: =D14-'Cash Flow Statement'!E14 -> 122206.61 | F14: =E14-'Cash Flow Statement'!F14 -> 123976.23 | G14: =F14-'Cash Flow Statement'!G14 -> 125929.73 | H14: =G14-'Cash Flow Statement'!H14 -> 128059.59
A15: Other Non-current Assets | B15: $mm | C15: 97618 | D15: ='Income Statement'!D9*Assumptions!D36 -> 109388.88 | E15: ='Income Statement'!E9*Assumptions!E36 -> 120398.54 | F15: ='Income Statement'!F9*Assumptions!F36 -> 130951.49 | G15: ='Income Statement'!G9*Assumptions!G36 -> 140652.34 | H15: ='Income Statement'!H9*Assumptions!H36 -> 149089.96
A16: Total Non-current Assets | B16: $mm | C16: =SUM(C13:C15) -> 352429 | D16: =SUM(D13:D15) -> 390845.9 | E16: =SUM(E13:E15) -> 429420.48 | F16: =SUM(F13:F15) -> 467933.34 | G16: =SUM(G13:G15) -> 505373.96 | H16: =SUM(H13:H15) -> 540647.78
A17: Total Assets | B17: $mm | C17: =C10+C16 -> 512163 | D17: =D10+D16 -> 611784.64 | E17: =E10+E16 -> 720246.03 | F17: =F10+F16 -> 838249.73 | G17: =G10+G16 -> 964866.84 | H17: =H10+H16 -> 1098771.9
A19: CURRENT LIABILITIES
A20: Current Liabilities | B20: $mm | C20: 125286 | D20: ='Income Statement'!D9*Assumptions!D25/365 -> 142163.29 | E20: ='Income Statement'!E9*Assumptions!E25/365 -> 159721.21 | F20: ='Income Statement'!F9*Assumptions!F25/365 -> 177446.3 | G20: ='Income Statement'!G9*Assumptions!G25/365 -> 194815.26 | H20: ='Income Statement'!H9*Assumptions!H25/365 -> 211235.09
A22: LONG-TERM LIABILITIES AND EQUITY
A23: Long-term Debt | B23: $mm | C23: 42688 | D23: =C23+'Cash Flow Statement'!D20 -> 42688 | E23: =D23+'Cash Flow Statement'!E20 -> 42688 | F23: =E23+'Cash Flow Statement'!F20 -> 42688 | G23: =F23+'Cash Flow Statement'!G20 -> 42688 | H23: =G23+'Cash Flow Statement'!H20 -> 42688
A24: Other Liabilities / Residual | B24: $mm | C24: 75712 | D24: =D17-D20-D23-D25 -> 90260.052 | E24: =E17-E20-E23-E25 -> 103726.12 | F24: =F17-F20-F23-F25 -> 116649.25 | G24: =G17-G20-G23-G25 -> 128547.71 | H24: =H17-H20-H23-H25 -> 138919.76
A25: Shareholders' Equity | B25: $mm | C25: 268477 | D25: =C25+'Income Statement'!D30+'Cash Flow Statement'!D8+'Cash Flow Statement'!D18+'Cash Flow Statement'!D19 -> 336673.3 | E25: =D25+'Income Statement'!E30+'Cash Flow Statement'!E8+'Cash Flow Statement'!E18+'Cash Flow Statement'!E19 -> 414110.7 | F25: =E25+'Income Statement'!F30+'Cash Flow Statement'!F8+'Cash Flow Statement'!F18+'Cash Flow Statement'!F19 -> 501466.18 | G25: =F25+'Income Statement'!G30+'Cash Flow Statement'!G8+'Cash Flow Statement'!G18+'Cash Flow Statement'!G19 -> 598815.87 | H25: =G25+'Income Statement'!H30+'Cash Flow Statement'!H8+'Cash Flow Statement'!H18+'Cash Flow Statement'!H19 -> 705929.03
A26: Total Liabilities & Equity | B26: $mm | C26: =C20+C23+C24+C25 -> 512163 | D26: =D20+D23+D24+D25 -> 611784.64 | E26: =E20+E23+E24+E25 -> 720246.03 | F26: =F20+F23+F24+F25 -> 838249.73 | G26: =G20+G23+G24+G25 -> 964866.84 | H26: =H20+H23+H24+H25 -> 1098771.9
A27: Balance Check | B27: $mm | C27: =C17-C26 -> 0 | D27: =D17-D26 -> 0 | E27: =E17-E26 -> 0 | F27: =F17-F26 -> 0 | G27: =G17-G26 -> 0 | H27: =H17-H26 -> 0

Sheet Cash Flow Statement
A1: Microsoft Corporation - Cash Flow Statement
A2: USD in millions; ending cash links directly to Balance Sheet cash
A4: Line Item | B4: Units | C4: FY24A | D4: FY25E | E4: FY26E | F4: FY27E | G4: FY28E | H4: FY29E
A5: OPERATING ACTIVITIES
A6: Net Income | B6: $mm | C6: 88136 | D6: ='Income Statement'!D30 -> 98407.984 | E6: ='Income Statement'!E30 -> 112121.33 | F6: ='Income Statement'!F30 -> 126855.72 | G6: ='Income Statement'!G30 -> 141781.08 | H6: ='Income Statement'!H30 -> 156448.63
A7: Depreciation & Amortization | B7: $mm | C7: 22287 | D7: ='Income Statement'!D9*Assumptions!D28 -> 25243.589 | E7: ='Income Statement'!E9*Assumptions!E28 -> 27881.768 | F7: ='Income Statement'!F9*Assumptions!F28 -> 30437.373 | G7: ='Income Statement'!G9*Assumptions!G28 -> 32818.879 | H7: ='Income Statement'!H9*Assumptions!H28 -> 34929.649
A8: Stock-Based Comp / Other Non-cash | B8: $mm | C8: 10734 | D8: ='Income Statement'!D9*Assumptions!D34 -> 11219.373 | E8: ='Income Statement'!E9*Assumptions!E34 -> 12356.693 | F8: ='Income Statement'!F9*Assumptions!F34 -> 13449.072 | G8: ='Income Statement'!G9*Assumptions!G34 -> 14455.935 | H8: ='Income Statement'!H9*Assumptions!H34 -> 15334.968
A9: Change in Working Capital | B9: $mm | C9: -2609 | D9: =-('Balance Sheet'!D7-'Balance Sheet'!C7)-('Balance Sheet'!D8-'Balance Sheet'!C8)+('Balance Sheet'!D20-'Balance Sheet'!C20) -> 9068.152 | E9: =-('Balance Sheet'!E7-'Balance Sheet'!D7)-('Balance Sheet'!E8-'Balance Sheet'!D8)+('Balance Sheet'!E20-'Balance Sheet'!D20) -> 9863.9152 | F9: =-('Balance Sheet'!F7-'Balance Sheet'!E7)-('Balance Sheet'!F8-'Balance Sheet'!E8)+('Balance Sheet'!F20-'Balance Sheet'!E20) -> 10071.587 | G9: =-('Balance Sheet'!G7-'Balance Sheet'!F7)-('Balance Sheet'!G8-'Balance Sheet'!F8)+('Balance Sheet'!G20-'Balance Sheet'!F20) -> 8930.7285 | H9: =-('Balance Sheet'!H7-'Balance Sheet'!G7)-('Balance Sheet'!H8-'Balance Sheet'!G8)+('Balance Sheet'!H20-'Balance Sheet'!G20) -> 9497.3908
A10: Net Cash Provided by Operating Activities | B10: $mm | C10: =SUM(C6:C9) -> 118548 | D10: =SUM(D6:D9) -> 143939.1 | E10: =SUM(E6:E9) -> 162223.71 | F10: =SUM(F6:F9) -> 180813.75 | G10: =SUM(G6:G9) -> 197986.62 | H10: =SUM(H6:H9) -> 216210.63
A12: INVESTING ACTIVITIES
A13: Capital Expenditures | B13: $mm | C13: -44477 | D13: =-'Income Statement'!D9*Assumptions!D29 -> -50487.178 | E13: =-'Income Statement'!E9*Assumptions!E29 -> -53862.507 | F13: =-'Income Statement'!F9*Assumptions!F29 -> -56627.671 | G13: =-'Income Statement'!G9*Assumptions!G29 -> -58605.14 | H13: =-'Income Statement'!H9*Assumptions!H29 -> -59635.985
A14: Acquisitions / Strategic Investments | B14: $mm | C14: -69132 | D14: =-'Income Statement'!D9*Assumptions!D30 -> -1402.4216 | E14: =-'Income Statement'!E9*Assumptions!E30 -> -1584.1914 | F14: =-'Income Statement'!F9*Assumptions!F30 -> -1769.6147 | G14: =-'Income Statement'!G9*Assumptions!G30 -> -1953.5047 | H14: =-'Income Statement'!H9*Assumptions!H30 -> -2129.8566
A15: Net Cash Used in Investing Activities | B15: $mm | C15: =SUM(C13:C14) -> -113609 | D15: =SUM(D13:D14) -> -51889.599 | E15: =SUM(E13:E14) -> -55446.698 | F15: =SUM(F13:F14) -> -58397.286 | G15: =SUM(G13:G14) -> -60558.645 | H15: =SUM(H13:H14) -> -61765.842
A17: FINANCING ACTIVITIES
A18: Dividends Paid | B18: $mm | C18: -21771 | D18: =-'Income Statement'!D30*Assumptions!D31 -> -24601.996 | E18: =-'Income Statement'!E30*Assumptions!E31 -> -28030.333 | F18: =-'Income Statement'!F30*Assumptions!F31 -> -31713.931 | G18: =-'Income Statement'!G30*Assumptions!G31 -> -35445.269 | H18: =-'Income Statement'!H30*Assumptions!H31 -> -39112.157
A19: Share Repurchases | B19: $mm | C19: -17254 | D19: =-'Income Statement'!D9*Assumptions!D32 -> -16829.059 | E19: =-'Income Statement'!E9*Assumptions!E32 -> -19010.297 | F19: =-'Income Statement'!F9*Assumptions!F32 -> -21235.377 | G19: =-'Income Statement'!G9*Assumptions!G32 -> -23442.056 | H19: =-'Income Statement'!H9*Assumptions!H32 -> -25558.279
A20: Debt Issuance / (Repayment), Net | B20: $mm | C20: 24395 | D20: =Assumptions!D33 -> 0 | E20: =Assumptions!E33 -> 0 | F20: =Assumptions!F33 -> 0 | G20: =Assumptions!G33 -> 0 | H20: =Assumptions!H33 -> 0
A21: Net Cash Used in Financing Activities | B21: $mm | C21: =SUM(C18:C20) -> -14630 | D21: =SUM(D18:D20) -> -41431.055 | E21: =SUM(E18:E20) -> -47040.63 | F21: =SUM(F18:F20) -> -52949.307 | G21: =SUM(G18:G20) -> -58887.325 | H21: =SUM(H18:H20) -> -64670.436
A23: Net Change in Cash | B23: $mm | C23: =C10+C15+C21 -> -9691 | D23: =D10+D15+D21 -> 50618.443 | E23: =E10+E15+E21 -> 59736.381 | F23: =F10+F15+F21 -> 69467.161 | G23: =G10+G15+G21 -> 78540.648 | H23: =H10+H15+H21 -> 89774.356
A24: Beginning Cash | B24: $mm | C24: 111262 | D24: ='Balance Sheet'!C6 -> 80500 | E24: ='Balance Sheet'!D6 -> 131118.44 | F24: ='Balance Sheet'!E6 -> 190854.82 | G24: ='Balance Sheet'!F6 -> 260321.99 | H24: ='Balance Sheet'!G6 -> 338862.63
A25: Ending Cash | B25: $mm | C25: 80500 | D25: =D24+D23 -> 131118.44 | E25: =E24+E23 -> 190854.82 | F25: =F24+F23 -> 260321.99 | G25: =G24+G23 -> 338862.63 | H25: =H24+H23 -> 428636.99
A26: Cash Check vs Balance Sheet | B26: $mm | C26: =C25-'Balance Sheet'!C6 -> 0 | D26: =D25-'Balance Sheet'!D6 -> 0 | E26: =E25-'Balance Sheet'!E6 -> 0 | F26: =F25-'Balance Sheet'!F6 -> 0 | G26: =G25-'Balance Sheet'!G6 -> 0 | H26: =H25-'Balance Sheet'!H6 -> 0
